{
  "category": "Resources",
  "url": "https://community.efecte.com/category/crisis-ops-resources",
  "updated": "2026-01-19T16:48:05.504923",
  "article_count": 7,
  "articles": [
    {
      "title": "Webinar and Q&A: Implementing Our Crisis Ops Solution",
      "slug": "webinar-and-q-a-implementing-our-crisis-ops-solution",
      "url": "https://community.efecte.com/t/g9hylfl/webinar-and-qa-implementing-our-crisis-ops-solution",
      "published": "2020-04-14T13:16:16.307Z",
      "updated": "2020-04-27T08:13:13.677000"
    },
    {
      "title": "Crisis Ops Installation Guidelines",
      "slug": "crisis-ops-installation-guidelines",
      "url": "https://community.efecte.com/t/h7hh758/crisis-ops-installation-guidelines",
      "published": "2020-03-23T10:28:09.577Z",
      "updated": "2020-04-20T10:03:28.430000"
    },
    {
      "title": "Crisis Ops Templates",
      "slug": "crisis-ops-templates",
      "url": "https://community.efecte.com/t/q6hh75x/crisis-ops-templates",
      "published": "2020-03-23T10:27:29.130Z",
      "updated": "2020-04-20T10:03:52.817000"
    },
    {
      "title": "Crisis Ops Solution Factsheet",
      "slug": "crisis-ops-solution-factsheet",
      "url": "https://community.efecte.com/t/h7hh7j2/crisis-ops-solution-factsheet",
      "published": "2020-03-23T10:01:00.000Z",
      "updated": "2020-03-25T06:52:17.370000"
    },
    {
      "title": "Mapping numeric attributes in ESS2",
      "slug": "mapping-numeric-attributes-in-ess2",
      "url": "https://community.efecte.com/t/y4ypztr",
      "published": "2025-12-22T15:05:45.897Z",
      "updated": "2025-12-22T16:05:45.897000"
    },
    {
      "title": "Suggestions to improve e-mail functionality in ESM",
      "slug": "suggestions-to-improve-e-mail-functionality-in-esm",
      "url": "https://community.efecte.com/t/h44anq",
      "published": "2019-10-23T18:31:43.267Z",
      "updated": "2019-10-23T21:00:32.750000"
    },
    {
      "title": "Improvements for Datacard history/change record feature",
      "slug": "improvements-for-datacard-history-change-record-feature",
      "url": "https://community.efecte.com/t/m1ypm2l",
      "published": "2025-12-16T08:52:37.660Z",
      "updated": "2025-12-16T09:59:55.733000"
    }
  ]
}